chidg/__init__.py
chidg/_chidg.so
chidg/chidg_classes.py
chidg/chidg_generate_driver.py
chidg/type_chidg.py
chidg/type_chidgvis_bc.py
chidg/type_dict.py
chidg-0.1.1.post17.data/scripts/chidggen
chidg-0.1.1.post17.dist-info/DESCRIPTION.rst
chidg-0.1.1.post17.dist-info/METADATA
chidg-0.1.1.post17.dist-info/RECORD
chidg-0.1.1.post17.dist-info/WHEEL
chidg-0.1.1.post17.dist-info/metadata.json
chidg-0.1.1.post17.dist-info/top_level.txt
