Metadata-Version: 2.0
Name: chidg
Version: 0.1.1.post17
Summary: A Chimera-based, discontinuous Galerkin solver
Home-page: https://github.com/nwukie/ChiDG
Author: Nathan A. Wukie
Author-email: nwukie@gmail.com
License: BSD 3-Clause
Keywords: finite element DG galerkin chimera
Platform: UNKNOWN
Requires-Dist: f90wrap (>=0.0.0)
